{
  "$schema": "https://mintlify.com/schema.json",
  "name": "AffEasy Docs",
  "openapi": "https://api.affeasy.link",
  "logo": {
    "dark": "/logo/logo-dark.svg",
    "light": "/logo/logo-light.svg"
  },
  "metadata": {
    "og:image": "https://affeasy.link/_static/thumbnail.jpg"
  },
  "feedback": {
    "raiseIssue": true,
    "suggestEdit": true,
    "thumbsRating": true
  },
  "favicon": "/favicon-32x32.png",
  "colors": {
    "primary": "#0D9373",
    "light": "#07C983",
    "dark": "#0D9373",
    "anchors": {
      "from": "#0D9373",
      "to": "#07C983"
    }
  },
  "topbarLinks": [
    {
      "name": "Support",
      "url": "mailto:support@affeasy.link"
    },
    {
      "name": "GitHub",
      "url": "https://github.com/afftester/afftester"
    }
  ],
  "topbarCtaButton": {
    "name": "Get Started",
    "url": "https://app.affeasy.link"
  },
  "tabs": [
    {
      "name": "API Reference",
      "url": "api-reference"
    }
  ],
  "anchors": [
    {
      "name": "GitHub",
      "icon": "github",
      "url": "https://github.com/afftester/afftester"
    }
  ],
  "navigation": [
    {
      "group": "Introduction",
      "pages": ["introduction", "how-it-works"]
    },
    {
      "group": "Quickstart Guide",
      "pages": [
        "quickstart/guide",
        {
          "group": "Connect an Affiliate Network",
          "pages": [
            "quickstart/affiliate-networks/introduction",
            "quickstart/affiliate-networks/rakuten",
            "quickstart/affiliate-networks/commision-junction",
            "quickstart/affiliate-networks/amazon"
          ]
        }
      ]
    },
    {
      "group": "Plans",
      "pages": ["plans/pro-plan", "plans/business-plan"]
    },
    {
      "group": "Features",
      "pages": [
        "features/how-to-redirect-root-domain",
        "features/custom-qr-codes",
        "features/custom-social-media-cards",
        "features/how-to-use-tags",
        "features/geo-targeting",
        "features/utm-builder",
        "features/link-comments",
        "features/device-targeting",
        "features/expiration-date",
        "features/link-cloaking",
        "features/password-protection",
        "features/search-indexing"
      ]
    },
    {
      "group": "Custom Domains",
      "pages": ["domains/add-custom-domain", "domains/cloudflare-domains"]
    },
    {
      "group": "Workspace",
      "pages": ["workspace/what-is-a-workspace", "workspace/get-workspace-id"]
    },
    {
      "group": "API Documentation",
      "icon": "code",
      "pages": ["api-reference/introduction"]
    }
  ],

  "footerSocials": {
    "website": "https://affeasy.link",
    "github": "https://github.com/afftester/afftester"
  }
}
